md_pdf_mcp/__init__.py
md_pdf_mcp/__main__.py
md_pdf_mcp/converter.py
md_pdf_mcp/server.py
md_pdf_mcp/vscode_styles.py
iflow_mcp_seanivore_md_pdf_mcp-0.1.0.dist-info/METADATA
iflow_mcp_seanivore_md_pdf_mcp-0.1.0.dist-info/WHEEL
iflow_mcp_seanivore_md_pdf_mcp-0.1.0.dist-info/entry_points.txt
iflow_mcp_seanivore_md_pdf_mcp-0.1.0.dist-info/RECORD
