Metadata-Version: 2.4
Name: iflow-mcp-seanivore-md-pdf-mcp
Version: 0.1.0
Summary: A Model Context Protocol (MCP) server that converts Markdown to gorgeously styled PDFs using VS Code's markdown styling and Python's ReportLab.
Author-email: seanivore <sean@aug.ltd>
Requires-Python: >=3.11
Requires-Dist: markdown>=3.7
Requires-Dist: mcp>=1.2.1
Requires-Dist: pillow>=9.0.0
Requires-Dist: reportlab>=4.3.0
